[
  {
    "id": "item0",
    "imageUrl": "assets/data/images/item_placeholder_d.png",
    "name": "Debug Coffee Mug",
    "description": "White ceramic mug, full of code and coffee (coffee not included)",
    "quantity": 1,
    "price": 45.0,
    "location": "Espoo",
    "sellerId": "user",
    "isSold": false,
    "buyerId":     null,
    "latitude": 60.2055,
    "longitude": 24.6559
  },
  {
    "id": "item1",
    "imageUrl": "assets/data/images/item_placeholder1.png",
    "name": "Coffee Mug",
    "description": "White ceramic mug, Helsinki Edition 1",
    "quantity": 1,
    "price": 5.0,
    "location": "Helsinki",
    "sellerId": "user",
    "isSold": true,
    "buyerId": "user_5678",
    "latitude": 60.2180,
    "longitude": 24.6702
  },
  {
    "id": "item2",
    "imageUrl": "assets/data/images/item_placeholder2.png",
    "name": "Coffee Mug",
    "description": "Glossy ceramic mug, Helsinki Edition 2",
    "quantity": 1,
    "price": 5.0,
    "location": "Helsinki",
    "sellerId": "user",
    "isSold": true,
    "buyerId": "user_5678",
    "latitude": 60.1683,
    "longitude": 24.9312
  },
  {
    "id": "item3",
    "imageUrl": "assets/data/images/item_placeholder3.png",
    "name": "Coffee Mug",
    "description": "Matte mug with handle, Helsinki Edition 3",
    "quantity": 1,
    "price": 5.0,
    "location": "Helsinki",
    "sellerId": "seller_default",
    "isSold": true,
    "buyerId": "user",
    "latitude": 60.1662,
    "longitude": 24.9277
  },
  {
    "id": "item4",
    "imageUrl": "assets/data/images/item_placeholder1.png",
    "name": "Coffee Mug",
    "description": "Minimalist design, Helsinki Edition 4",
    "quantity": 1,
    "price": 5.0,
    "location": "Helsinki",
    "sellerId": "seller_default",
    "isSold": false,
    "buyerId": null,
    "latitude": 60.1708,
    "longitude": 24.9421
  },
  {
    "id": "item5",
    "imageUrl": "assets/data/images/item_placeholder2.png",
    "name": "Coffee Mug",
    "description": "Tall mug for big mornings, Helsinki Edition 5",
    "quantity": 1,
    "price": 5.0,
    "location": "Helsinki",
    "sellerId": "seller_default",
    "isSold": false,
    "buyerId": null,
    "latitude": 60.1695,
    "longitude": 24.9354
  },

  {
    "id": "item6",
    "imageUrl": "assets/data/images/item_placeholder3.png",
    "name": "Coffee Mug",
    "description": "Espoo Edition 1 – classic handle",
    "quantity": 1,
    "price": 5.0,
    "location": "Espoo",
    "sellerId": "seller_default",
    "isSold": false,
    "buyerId": null,
    "latitude": 60.2201,
    "longitude": 24.6488
  },
  {
    "id": "item7",
    "imageUrl": "assets/data/images/item_placeholder1.png",
    "name": "Coffee Mug",
    "description": "Espoo Edition 2 – wide rim design",
    "quantity": 1,
    "price": 5.0,
    "location": "Espoo",
    "sellerId": "seller_default",
    "isSold": false,
    "buyerId": null,
    "latitude": 60.2149,
    "longitude": 24.6591
  },
  {
    "id": "item8",
    "imageUrl": "assets/data/images/item_placeholder2.png",
    "name": "Coffee Mug",
    "description": "Espoo Edition 3 – vintage finish",
    "quantity": 1,
    "price": 5.0,
    "location": "Espoo",
    "sellerId": "seller_default",
    "isSold": false,
    "buyerId": null,
    "latitude": 60.2114,
    "longitude": 24.6681
  },
  {
    "id": "item9",
    "imageUrl": "assets/data/images/item_placeholder3.png",
    "name": "Coffee Mug",
    "description": "Espoo Edition 4 – studio glaze",
    "quantity": 1,
    "price": 5.0,
    "location": "Helsinki",
    "sellerId": "seller_default",
    "isSold": false,
    "buyerId": null,
    "latitude": 60.1651,
    "longitude": 24.9339
  },
  {
    "id": "item10",
    "imageUrl": "assets/data/images/item_placeholder1.png",
    "name": "Coffee Mug",
    "description": "Espoo Edition 5 – flat bottom",
    "quantity": 1,
    "price": 5.0,
    "location": "Espoo",
    "sellerId": "seller_default",
    "isSold": false,
    "buyerId": null,
    "latitude": 60.2098,
    "longitude": 24.6625
  },

  {
    "id": "item11",
    "imageUrl": "assets/data/images/item_placeholder2.png",
    "name": "Coffee Mug",
    "description": "Vantaa Edition 1 – travel style",
    "quantity": 1,
    "price": 5.0,
    "location": "Vantaa",
    "sellerId": "seller_default",
    "isSold": false,
    "buyerId": null,
    "latitude": 60.2934,
    "longitude": 25.0378
  },
  {
    "id": "item12",
    "imageUrl": "assets/data/images/item_placeholder3.png",
    "name": "Coffee Mug",
    "description": "Vantaa Edition 2 – hand-painted",
    "quantity": 1,
    "price": 5.0,
    "location": "Vantaa",
    "sellerId": "seller_default",
    "isSold": false,
    "buyerId": null,
    "latitude": 60.2978,
    "longitude": 25.0453
  },
  {
    "id": "item13",
    "imageUrl": "assets/data/images/item_placeholder1.png",
    "name": "Coffee Mug",
    "description": "Vantaa Edition 3 – thick ceramic",
    "quantity": 1,
    "price": 5.0,
    "location": "Vantaa",
    "sellerId": "seller_default",
    "isSold": false,
    "buyerId": null,
    "latitude": 60.2952,
    "longitude": 25.0305
  },
  {
    "id": "item14",
    "imageUrl": "assets/data/images/item_placeholder2.png",
    "name": "Coffee Mug",
    "description": "Vantaa Edition 4 – dishwasher safe",
    "quantity": 1,
    "price": 5.0,
    "location": "Vantaa",
    "sellerId": "seller_default",
    "isSold": false,
    "buyerId": null,
    "latitude": 60.2921,
    "longitude": 25.0360
  },
  {
    "id": "item15",
    "imageUrl": "assets/data/images/item_placeholder3.png",
    "name": "Coffee Mug",
    "description": "Vantaa Edition 5 – smooth edges",
    "quantity": 1,
    "price": 5.0,
    "location": "Vantaa",
    "sellerId": "seller_default",
    "isSold": false,
    "buyerId": null,
    "latitude": 60.2912,
    "longitude": 25.0422
  },

  {
    "id": "item16",
    "imageUrl": "assets/data/images/item_placeholder1.png",
    "name": "Coffee Mug",
    "description": "Stockholm Edition 1 – frost finish",
    "quantity": 1,
    "price": 5.0,
    "location": "Stockholm",
    "sellerId": "seller_default",
    "isSold": false,
    "buyerId": null,
    "latitude": 59.3293,
    "longitude": 18.0686
  },
  {
    "id": "item17",
    "imageUrl": "assets/data/images/item_placeholder2.png",
    "name": "Coffee Mug",
    "description": "Stockholm Edition 2 – modern design",
    "quantity": 1,
    "price": 5.0,
    "location": "Stockholm",
    "sellerId": "seller_default",
    "isSold": false,
    "buyerId": null,
    "latitude": 59.3252,
    "longitude": 18.0703
  },
  {
    "id": "item18",
    "imageUrl": "assets/data/images/item_placeholder3.png",
    "name": "Coffee Mug",
    "description": "Stockholm Edition 3 – charcoal glaze",
    "quantity": 1,
    "price": 5.0,
    "location": "Stockholm",
    "sellerId": "seller_default",
    "isSold": false,
    "buyerId": null,
    "latitude": 59.3275,
    "longitude": 18.0632
  },
  {
    "id": "item19",
    "imageUrl": "assets/data/images/item_placeholder1.png",
    "name": "Coffee Mug",
    "description": "Stockholm Edition 4 – designer series",
    "quantity": 1,
    "price": 5.0,
    "location": "Stockholm",
    "sellerId": "seller_default",
    "isSold": false,
    "buyerId": null,
    "latitude": 59.3288,
    "longitude": 18.0651
  },
  {
    "id": "item20",
    "imageUrl": "assets/data/images/item_placeholder2.png",
    "name": "Coffee Mug",
    "description": "Stockholm Edition 5 – textured matte",
    "quantity": 1,
    "price": 5.0,
    "location": "Stockholm",
    "sellerId": "seller_default",
    "isSold": false,
    "buyerId": null,
    "latitude": 59.3300,
    "longitude": 18.0615
  }
]